scigym/__init__.py
scigym/version.py
scigym/envs/__init__.py
scigym/envs/tests/__init__.py
scigym/envs/tests/spec_list.py
scigym/envs/tests/test_determinism.py
scigym/envs/tests/test_envs.py
scigym-0.0.3.dist-info/LICENSE
scigym-0.0.3.dist-info/METADATA
scigym-0.0.3.dist-info/WHEEL
scigym-0.0.3.dist-info/top_level.txt
scigym-0.0.3.dist-info/RECORD
