Metadata-Version: 2.1
Name: scigym
Version: 0.0.3
Summary: SciGym -- The OpenAI Gym for Science: A platform for your scientific reinforcement learning problem.
Home-page: https://github.com/HendrikPN/scigym
Author: HendrikPN
Author-email: hendrik.poulsen-nautrup@uibk.ac.at
License: MIT
Platform: UNKNOWN
License-File: LICENSE
Requires-Dist: gym (==0.18.0)
Provides-Extra: all
Requires-Dist: matplotlib (==3.4.2) ; extra == 'all'
Provides-Extra: entangled_ions
Provides-Extra: teleportation
Provides-Extra: toricgame
Requires-Dist: matplotlib (==3.4.2) ; extra == 'toricgame'
